.gitignore
MANIFEST.in
README.md
dump.rdb
pytest.ini
requirements.txt
runtests.py
setup.py
django_oscar_webpay.egg-info/PKG-INFO
django_oscar_webpay.egg-info/SOURCES.txt
django_oscar_webpay.egg-info/dependency_links.txt
django_oscar_webpay.egg-info/requires.txt
django_oscar_webpay.egg-info/top_level.txt
oscar_webpay/__init__.py
oscar_webpay/admin.py
oscar_webpay/apps.py
oscar_webpay/gateway.py
oscar_webpay/models.py
oscar_webpay/oscar_webpay_settings.py
oscar_webpay/urls.py
oscar_webpay/views.py
oscar_webpay/certificates/__init__.py
oscar_webpay/certificates/cert_capture.py
oscar_webpay/certificates/cert_complete.py
oscar_webpay/certificates/cert_normal.py
oscar_webpay/certificates/cert_normal_mall.py
oscar_webpay/certificates/cert_oneclick.py
oscar_webpay/dashboard/__init__.py
oscar_webpay/dashboard/app.py
oscar_webpay/dashboard/views.py
oscar_webpay/exceptions/__init__.py
oscar_webpay/exceptions/common.py
oscar_webpay/exceptions/soap_exceptions.py
oscar_webpay/exceptions/utils.py
oscar_webpay/libwebpay/__init__.py
oscar_webpay/libwebpay/configuration.py
oscar_webpay/libwebpay/webpay.py
oscar_webpay/libwebpay/webpay_capture.py
oscar_webpay/libwebpay/webpay_complete.py
oscar_webpay/libwebpay/webpay_mall_normal.py
oscar_webpay/libwebpay/webpay_normal.py
oscar_webpay/libwebpay/webpay_nullify.py
oscar_webpay/libwebpay/webpay_oneclick.py
oscar_webpay/locale/es/LC_MESSAGES/django.mo
oscar_webpay/migrations/0001_initial.py
oscar_webpay/migrations/0002_auto_20170710_1156.py
oscar_webpay/migrations/0003_remove_webpaytransaction_base_transaction.py
oscar_webpay/migrations/0004_webpaytransaction_result_auth_code.py
oscar_webpay/migrations/0005_auto_20170731_1820.py
oscar_webpay/migrations/0006_auto_20170810_1612.py
oscar_webpay/migrations/__init__.py
oscar_webpay/templates/oscar_webpay/checkout/webpay_form.html
oscar_webpay/templates/oscar_webpay/checkout/webpay_preview.html
oscar_webpay/templates/oscar_webpay/dashboard/transaction_detail.html
oscar_webpay/templates/oscar_webpay/dashboard/transaction_list.html