Metadata-Version: 1.1
Name: django-oscar-webpay
Version: 0.4.3
Summary: An application for intagrating WebPay with oscar based e-commerce sites
Home-page: https://github.com/RaydelMiranda/django-oscar-webpay
Author: Raydel Miranda
Author-email: raydel.miranda.gomez@gmail.com
License: LGPL
Keywords: development web django webpay ecommerce
Platform: UNKNOWN
Classifier: Development Status :: 4 - Beta
Classifier: Intended Audience :: Developers
Classifier: Topic :: Software Development
Classifier: Environment :: Web Environment
Classifier: License :: OSI Approved :: MIT License
Classifier: Programming Language :: Python :: 2.7
Classifier: Programming Language :: Python :: 3
Classifier: Programming Language :: Python :: 3.3
Classifier: Programming Language :: Python :: 3.4
Classifier: Programming Language :: Python :: 3.5
